{
	"name": "Avatar0",
	"plugin-id": "Sprite",
	"sid": 895006526317252,
	"isGlobal": false,
	"instanceVariables": [],
	"behaviorTypes": [],
	"effectTypes": [],
	"animations": {
		"items": [
			{
				"frames": [
					{
						"width": 100,
						"height": 100,
						"originX": 0.5,
						"originY": 0.89,
						"originalSource": "",
						"exportFormat": "png",
						"exportQuality": 0.8,
						"imageSpriteId": 7216436,
						"collisionPoly": {
							"points": [
								0.20687500000000025,
								0.8122727272727274,
								0.8025000000000004,
								0.8136363636363638,
								0.8181250000000001,
								1,
								0.1649999999999998,
								1
							]
						},
						"useCollisionPoly": true,
						"imagePoints": [
							{
								"name": "Egg",
								"x": 0.37,
								"y": 0.43
							}
						],
						"duration": 1
					}
				],
				"sid": 367541075582286,
				"name": "Idle",
				"isLooping": false,
				"isPingPong": false,
				"repeatCount": 1,
				"repeatTo": 0,
				"speed": 5
			},
			{
				"frames": [
					{
						"width": 100,
						"height": 100,
						"originX": 0.5,
						"originY": 0.87,
						"originalSource": "",
						"exportFormat": "png",
						"exportQuality": 0.8,
						"imageSpriteId": 6697315,
						"collisionPoly": {
							"points": [
								0.6924999999999996,
								0.9174999999999998,
								0.1687499999999999,
								0.9250000000000003,
								0.16374999999999962,
								0.6129545454545451,
								0.6931249999999998,
								0.6129545454545455
							]
						},
						"useCollisionPoly": true,
						"imagePoints": [
							{
								"name": "Egg",
								"x": 0.35,
								"y": 0.44
							}
						],
						"duration": 1
					},
					{
						"width": 100,
						"height": 100,
						"originX": 0.5,
						"originY": 0.87,
						"originalSource": "",
						"exportFormat": "png",
						"exportQuality": 0.8,
						"imageSpriteId": 8572854,
						"collisionPoly": {
							"points": [
								0.6924999999999996,
								0.9174999999999998,
								0.1687499999999999,
								0.9250000000000003,
								0.16374999999999962,
								0.6129545454545451,
								0.6931249999999998,
								0.6129545454545455
							]
						},
						"useCollisionPoly": true,
						"imagePoints": [
							{
								"name": "Egg",
								"x": 0.35,
								"y": 0.44
							}
						],
						"duration": 1
					},
					{
						"width": 100,
						"height": 100,
						"originX": 0.5,
						"originY": 0.87,
						"originalSource": "",
						"exportFormat": "png",
						"exportQuality": 0.8,
						"imageSpriteId": 975777,
						"collisionPoly": {
							"points": [
								0.6924999999999996,
								0.9174999999999998,
								0.1687499999999999,
								0.9250000000000003,
								0.16374999999999962,
								0.6129545454545451,
								0.6931249999999998,
								0.6129545454545455
							]
						},
						"useCollisionPoly": true,
						"imagePoints": [
							{
								"name": "Egg",
								"x": 0.35,
								"y": 0.44
							}
						],
						"duration": 1
					},
					{
						"width": 100,
						"height": 100,
						"originX": 0.5,
						"originY": 0.87,
						"originalSource": "",
						"exportFormat": "png",
						"exportQuality": 0.8,
						"imageSpriteId": 5113694,
						"collisionPoly": {
							"points": [
								0.6924999999999996,
								0.9174999999999998,
								0.1687499999999999,
								0.9250000000000003,
								0.16374999999999962,
								0.6129545454545451,
								0.6931249999999998,
								0.6129545454545455
							]
						},
						"useCollisionPoly": true,
						"imagePoints": [
							{
								"name": "Egg",
								"x": 0.35,
								"y": 0.44
							}
						],
						"duration": 1
					},
					{
						"width": 100,
						"height": 100,
						"originX": 0.5,
						"originY": 0.87,
						"originalSource": "",
						"exportFormat": "png",
						"exportQuality": 0.8,
						"imageSpriteId": 7080985,
						"collisionPoly": {
							"points": [
								0.6924999999999996,
								0.9174999999999998,
								0.1687499999999999,
								0.9250000000000003,
								0.16374999999999962,
								0.6129545454545451,
								0.6931249999999998,
								0.6129545454545455
							]
						},
						"useCollisionPoly": true,
						"imagePoints": [
							{
								"name": "Egg",
								"x": 0.35,
								"y": 0.44
							}
						],
						"duration": 1
					},
					{
						"width": 100,
						"height": 100,
						"originX": 0.5,
						"originY": 0.87,
						"originalSource": "",
						"exportFormat": "png",
						"exportQuality": 0.8,
						"imageSpriteId": 1518984,
						"collisionPoly": {
							"points": [
								0.6924999999999996,
								0.9174999999999998,
								0.1687499999999999,
								0.9250000000000003,
								0.16374999999999962,
								0.6129545454545451,
								0.6931249999999998,
								0.6129545454545455
							]
						},
						"useCollisionPoly": true,
						"imagePoints": [
							{
								"name": "Egg",
								"x": 0.35,
								"y": 0.44
							}
						],
						"duration": 1
					},
					{
						"width": 100,
						"height": 100,
						"originX": 0.5,
						"originY": 0.87,
						"originalSource": "",
						"exportFormat": "png",
						"exportQuality": 0.8,
						"imageSpriteId": 9444733,
						"collisionPoly": {
							"points": [
								0.6924999999999996,
								0.9174999999999998,
								0.1687499999999999,
								0.9250000000000003,
								0.16374999999999962,
								0.6129545454545451,
								0.6931249999999998,
								0.6129545454545455
							]
						},
						"useCollisionPoly": true,
						"imagePoints": [
							{
								"name": "Egg",
								"x": 0.35,
								"y": 0.44
							}
						],
						"duration": 1
					},
					{
						"width": 100,
						"height": 100,
						"originX": 0.5,
						"originY": 0.87,
						"originalSource": "",
						"exportFormat": "png",
						"exportQuality": 0.8,
						"imageSpriteId": 970287,
						"collisionPoly": {
							"points": [
								0.6924999999999996,
								0.9174999999999998,
								0.1687499999999999,
								0.9250000000000003,
								0.16374999999999962,
								0.6129545454545451,
								0.6931249999999998,
								0.6129545454545455
							]
						},
						"useCollisionPoly": true,
						"imagePoints": [
							{
								"name": "Egg",
								"x": 0.35,
								"y": 0.44
							}
						],
						"duration": 1
					},
					{
						"width": 100,
						"height": 100,
						"originX": 0.5,
						"originY": 0.87,
						"originalSource": "",
						"exportFormat": "png",
						"exportQuality": 0.8,
						"imageSpriteId": 6695876,
						"collisionPoly": {
							"points": [
								0.6924999999999996,
								0.9174999999999998,
								0.1687499999999999,
								0.9250000000000003,
								0.16374999999999962,
								0.6129545454545451,
								0.6931249999999998,
								0.6129545454545455
							]
						},
						"useCollisionPoly": true,
						"imagePoints": [
							{
								"name": "Egg",
								"x": 0.35,
								"y": 0.44
							}
						],
						"duration": 1
					},
					{
						"width": 100,
						"height": 100,
						"originX": 0.5,
						"originY": 0.87,
						"originalSource": "",
						"exportFormat": "png",
						"exportQuality": 0.8,
						"imageSpriteId": 54433,
						"collisionPoly": {
							"points": [
								0.6924999999999996,
								0.9174999999999998,
								0.1687499999999999,
								0.9250000000000003,
								0.16374999999999962,
								0.6129545454545451,
								0.6931249999999998,
								0.6129545454545455
							]
						},
						"useCollisionPoly": true,
						"imagePoints": [
							{
								"name": "Egg",
								"x": 0.35,
								"y": 0.44
							}
						],
						"duration": 1
					}
				],
				"sid": 392702367070765,
				"name": "Walk Right",
				"isLooping": true,
				"isPingPong": false,
				"repeatCount": 1,
				"repeatTo": 0,
				"speed": 16
			},
			{
				"frames": [
					{
						"width": 100,
						"height": 100,
						"originX": 0.5,
						"originY": 0.85,
						"originalSource": "",
						"exportFormat": "png",
						"exportQuality": 0.8,
						"imageSpriteId": 9634067,
						"collisionPoly": {
							"points": [
								0.31000000000000005,
								0.31,
								0.5,
								0.06,
								0.69,
								0.3,
								0.58,
								0.5,
								0.63,
								0.63,
								0.5,
								0.66,
								0.37,
								0.62,
								0.28,
								0.5
							]
						},
						"useCollisionPoly": true,
						"imagePoints": [
							{
								"name": "Egg",
								"x": 0.5,
								"y": 0.5
							}
						],
						"duration": 1
					},
					{
						"width": 100,
						"height": 100,
						"originX": 0.5,
						"originY": 0.85,
						"originalSource": "",
						"exportFormat": "png",
						"exportQuality": 0.8,
						"imageSpriteId": 2650162,
						"collisionPoly": {
							"points": [
								0.30000000000000004,
								0.3,
								0.5,
								0.09,
								0.68,
								0.31,
								0.75,
								0.5,
								0.61,
								0.61,
								0.5,
								0.75,
								0.36,
								0.63,
								0.3400000000000001,
								0.5
							]
						},
						"useCollisionPoly": true,
						"imagePoints": [
							{
								"name": "Egg",
								"x": 0.5,
								"y": 0.5
							}
						],
						"duration": 1
					},
					{
						"width": 100,
						"height": 100,
						"originX": 0.5,
						"originY": 0.85,
						"originalSource": "",
						"exportFormat": "png",
						"exportQuality": 0.8,
						"imageSpriteId": 648928,
						"collisionPoly": {
							"points": [
								0.30000000000000004,
								0.3,
								0.5,
								0.08,
								0.67,
								0.32,
								0.67,
								0.5,
								0.62,
								0.62,
								0.5,
								0.8,
								0.37,
								0.62,
								0.42999999999999994,
								0.5
							]
						},
						"useCollisionPoly": true,
						"imagePoints": [
							{
								"name": "Egg",
								"x": 0.5,
								"y": 0.5
							}
						],
						"duration": 1
					},
					{
						"width": 100,
						"height": 100,
						"originX": 0.5,
						"originY": 0.85,
						"originalSource": "",
						"exportFormat": "png",
						"exportQuality": 0.8,
						"imageSpriteId": 4891721,
						"collisionPoly": {
							"points": [
								0.30000000000000004,
								0.3,
								0.5,
								0.08,
								0.68,
								0.31,
								0.66,
								0.5,
								0.63,
								0.63,
								0.5,
								0.8,
								0.42999999999999994,
								0.56,
								0.43999999999999995,
								0.5
							]
						},
						"useCollisionPoly": true,
						"imagePoints": [
							{
								"name": "Egg",
								"x": 0.5,
								"y": 0.5
							}
						],
						"duration": 1
					},
					{
						"width": 100,
						"height": 100,
						"originX": 0.5,
						"originY": 0.85,
						"originalSource": "",
						"exportFormat": "png",
						"exportQuality": 0.8,
						"imageSpriteId": 1221590,
						"collisionPoly": {
							"points": [
								0.30000000000000004,
								0.3,
								0.5,
								0.08,
								0.68,
								0.31,
								0.75,
								0.5,
								0.65,
								0.65,
								0.5,
								0.89,
								0.47,
								0.52,
								0.44999999999999996,
								0.5
							]
						},
						"useCollisionPoly": true,
						"imagePoints": [
							{
								"name": "Egg",
								"x": 0.5,
								"y": 0.5
							}
						],
						"duration": 1
					},
					{
						"width": 100,
						"height": 100,
						"originX": 0.5,
						"originY": 0.85,
						"originalSource": "",
						"exportFormat": "png",
						"exportQuality": 0.8,
						"imageSpriteId": 7550189,
						"collisionPoly": {
							"points": [
								0.31000000000000005,
								0.31,
								0.5,
								0.07,
								0.68,
								0.31,
								0.82,
								0.5,
								0.63,
								0.63,
								0.5,
								0.81,
								0.42999999999999994,
								0.56,
								0.42999999999999994,
								0.5
							]
						},
						"useCollisionPoly": true,
						"imagePoints": [
							{
								"name": "Egg",
								"x": 0.5,
								"y": 0.5
							}
						],
						"duration": 1
					},
					{
						"width": 100,
						"height": 100,
						"originX": 0.5,
						"originY": 0.85,
						"originalSource": "",
						"exportFormat": "png",
						"exportQuality": 0.8,
						"imageSpriteId": 5545419,
						"collisionPoly": {
							"points": [
								0.31000000000000005,
								0.31,
								0.5,
								0.06,
								0.68,
								0.31,
								0.83,
								0.5,
								0.63,
								0.63,
								0.5,
								0.66,
								0.39,
								0.6,
								0.42999999999999994,
								0.5
							]
						},
						"useCollisionPoly": true,
						"imagePoints": [
							{
								"name": "Egg",
								"x": 0.5,
								"y": 0.5
							}
						],
						"duration": 1
					},
					{
						"width": 100,
						"height": 100,
						"originX": 0.5,
						"originY": 0.85,
						"originalSource": "",
						"exportFormat": "png",
						"exportQuality": 0.8,
						"imageSpriteId": 7553312,
						"collisionPoly": {
							"points": [
								0.31000000000000005,
								0.31,
								0.5,
								0.08,
								0.68,
								0.31,
								0.6,
								0.5,
								0.62,
								0.62,
								0.5,
								0.7,
								0.35,
								0.64,
								0.27,
								0.5
							]
						},
						"useCollisionPoly": true,
						"imagePoints": [
							{
								"name": "Egg",
								"x": 0.5,
								"y": 0.5
							}
						],
						"duration": 1
					},
					{
						"width": 100,
						"height": 100,
						"originX": 0.5,
						"originY": 0.85,
						"originalSource": "",
						"exportFormat": "png",
						"exportQuality": 0.8,
						"imageSpriteId": 1930759,
						"collisionPoly": {
							"points": [
								0.31000000000000005,
								0.31,
								0.5,
								0.1,
								0.68,
								0.31,
								0.6,
								0.5,
								0.62,
								0.62,
								0.5,
								0.7,
								0.35,
								0.64,
								0.27,
								0.5
							]
						},
						"useCollisionPoly": true,
						"imagePoints": [
							{
								"name": "Egg",
								"x": 0.5,
								"y": 0.5
							}
						],
						"duration": 1
					}
				],
				"sid": 943448543209340,
				"name": "Walk Up",
				"isLooping": true,
				"isPingPong": false,
				"repeatCount": 1,
				"repeatTo": 0,
				"speed": 16
			},
			{
				"frames": [
					{
						"width": 100,
						"height": 100,
						"originX": 0.48,
						"originY": 0.86,
						"originalSource": "",
						"exportFormat": "png",
						"exportQuality": 0.8,
						"imageSpriteId": 3209886,
						"collisionPoly": {
							"points": [
								0.1537499999999996,
								0.835,
								0.8556250000000004,
								0.8363636363636363,
								0.8275000000000001,
								0.9997727272727277,
								0.1525000000000002,
								1
							]
						},
						"useCollisionPoly": true,
						"imagePoints": [
							{
								"name": "Egg",
								"x": 0.42,
								"y": 0.39
							}
						],
						"duration": 1
					},
					{
						"width": 100,
						"height": 100,
						"originX": 0.48,
						"originY": 0.86,
						"originalSource": "",
						"exportFormat": "png",
						"exportQuality": 0.8,
						"imageSpriteId": 8183745,
						"collisionPoly": {
							"points": [
								0.6699999999999999,
								0.5,
								0.63,
								0.62,
								0.5,
								0.69,
								0.39,
								0.61,
								0.4,
								0.5,
								0.31999999999999995,
								0.31,
								0.5,
								0.04,
								0.69,
								0.31
							]
						},
						"useCollisionPoly": true,
						"imagePoints": [
							{
								"name": "Egg",
								"x": 0.42,
								"y": 0.39
							}
						],
						"duration": 1
					},
					{
						"width": 100,
						"height": 100,
						"originX": 0.48,
						"originY": 0.86,
						"originalSource": "",
						"exportFormat": "png",
						"exportQuality": 0.8,
						"imageSpriteId": 5684187,
						"collisionPoly": {
							"points": [
								0.64,
								0.5,
								0.62,
								0.61,
								0.5,
								0.74,
								0.41000000000000003,
								0.59,
								0.25,
								0.5,
								0.32999999999999996,
								0.32,
								0.5,
								0.09,
								0.7,
								0.3
							]
						},
						"useCollisionPoly": true,
						"imagePoints": [
							{
								"name": "Egg",
								"x": 0.42,
								"y": 0.39
							}
						],
						"duration": 1
					},
					{
						"width": 100,
						"height": 100,
						"originX": 0.48,
						"originY": 0.86,
						"originalSource": "",
						"exportFormat": "png",
						"exportQuality": 0.8,
						"imageSpriteId": 187333,
						"collisionPoly": {
							"points": [
								0.76,
								0.5,
								0.64,
								0.63,
								0.5,
								0.82,
								0.4,
								0.6,
								0.32999999999999996,
								0.5,
								0.32999999999999996,
								0.32,
								0.5,
								0.08,
								0.7,
								0.3
							]
						},
						"useCollisionPoly": true,
						"imagePoints": [
							{
								"name": "Egg",
								"x": 0.42,
								"y": 0.39
							}
						],
						"duration": 1
					},
					{
						"width": 100,
						"height": 100,
						"originX": 0.48,
						"originY": 0.86,
						"originalSource": "",
						"exportFormat": "png",
						"exportQuality": 0.8,
						"imageSpriteId": 4403516,
						"collisionPoly": {
							"points": [
								0.5800000000000001,
								0.5,
								0.5800000000000001,
								0.57,
								0.5,
								0.86,
								0.36,
								0.64,
								0.33999999999999997,
								0.5,
								0.31999999999999995,
								0.31,
								0.5,
								0.08,
								0.7,
								0.3
							]
						},
						"useCollisionPoly": true,
						"imagePoints": [
							{
								"name": "Egg",
								"x": 0.42,
								"y": 0.39
							}
						],
						"duration": 1
					},
					{
						"width": 100,
						"height": 100,
						"originX": 0.48,
						"originY": 0.86,
						"originalSource": "",
						"exportFormat": "png",
						"exportQuality": 0.8,
						"imageSpriteId": 8752731,
						"collisionPoly": {
							"points": [
								0.76,
								0.5,
								0.56,
								0.55,
								0.5,
								0.73,
								0.35,
								0.65,
								0.25,
								0.5,
								0.31999999999999995,
								0.31,
								0.5,
								0.08,
								0.69,
								0.31
							]
						},
						"useCollisionPoly": true,
						"imagePoints": [
							{
								"name": "Egg",
								"x": 0.42,
								"y": 0.39
							}
						],
						"duration": 1
					},
					{
						"width": 100,
						"height": 100,
						"originX": 0.48,
						"originY": 0.86,
						"originalSource": "",
						"exportFormat": "png",
						"exportQuality": 0.8,
						"imageSpriteId": 2702986,
						"collisionPoly": {
							"points": [
								0.75,
								0.5,
								0.56,
								0.55,
								0.5,
								0.75,
								0.35,
								0.65,
								0.18000000000000005,
								0.5,
								0.31999999999999995,
								0.31,
								0.5,
								0.07,
								0.69,
								0.31
							]
						},
						"useCollisionPoly": true,
						"imagePoints": [
							{
								"name": "Egg",
								"x": 0.42,
								"y": 0.39
							}
						],
						"duration": 1
					},
					{
						"width": 100,
						"height": 100,
						"originX": 0.48,
						"originY": 0.86,
						"originalSource": "",
						"exportFormat": "png",
						"exportQuality": 0.8,
						"imageSpriteId": 12232,
						"collisionPoly": {
							"points": [
								0.73,
								0.5,
								0.62,
								0.61,
								0.5,
								0.77,
								0.37,
								0.63,
								0.17000000000000004,
								0.5,
								0.31999999999999995,
								0.31,
								0.5,
								0.07,
								0.69,
								0.31
							]
						},
						"useCollisionPoly": true,
						"imagePoints": [
							{
								"name": "Egg",
								"x": 0.42,
								"y": 0.39
							}
						],
						"duration": 1
					},
					{
						"width": 100,
						"height": 100,
						"originX": 0.48,
						"originY": 0.86,
						"originalSource": "",
						"exportFormat": "png",
						"exportQuality": 0.8,
						"imageSpriteId": 6455460,
						"collisionPoly": {
							"points": [
								0.69,
								0.5,
								0.65,
								0.64,
								0.5,
								0.76,
								0.41000000000000003,
								0.59,
								0.38,
								0.5,
								0.32999999999999996,
								0.32,
								0.5,
								0.06,
								0.6799999999999999,
								0.32
							]
						},
						"useCollisionPoly": true,
						"imagePoints": [
							{
								"name": "Egg",
								"x": 0.42,
								"y": 0.39
							}
						],
						"duration": 1
					}
				],
				"sid": 933505465723914,
				"name": "Walk Down",
				"isLooping": true,
				"isPingPong": false,
				"repeatCount": 1,
				"repeatTo": 0,
				"speed": 16
			}
		],
		"subfolders": []
	}
}